# synchronized 关键字原理

众所周知 `synchronized` 关键字是解决并发问题常用解决方案，有以下三种使用方式:

- 同步普通方法，锁的是当前对象。
- 同步静态方法，锁的是当前 `Class` 对象。
- 同步块，锁的是 `()` 中的对象。

实现原理： `JVM` 是通过进入、退出对象监视器( `Monitor` )来实现对方法、同步块的同步的。

具体实现是在编译之后在同步方法调用前加入一个 `monitor.enter` 指令，在退出方法和异常处插入 `monitor.exit` 的指令。

其本质就是对一个对象监视器( `Monitor` )进行获取，而这个获取过程具有排他性从而达到了同一时刻只能一个线程访问的目的。

而对于没有获取到锁的线程将会阻塞到方法入口处，直到获取锁的线程 `monitor.exit` 之后才能尝试继续获取锁

通过一段代码来演示:

```java
    public static void main(String[] args) {
        synchronized (Synchronize.class){
            System.out.println("Synchronize");
        }
    }
```

使用 `javap -c Synchronize` 可以查看编译之后的具体信息。

```java
public class com.crossoverjie.synchronize.Synchronize {
  public com.crossoverjie.synchronize.Synchronize();
    Code:
       0: aload_0
       1: invokespecial #1                  // Method java/lang/Object."<init>":()V
       4: return

  public static void main(java.lang.String[]);
    Code:
       0: ldc           #2                  // class com/crossoverjie/synchronize/Synchronize
       2: dup
       3: astore_1
       **4: monitorenter**
       5: getstatic     #3                  // Field java/lang/System.out:Ljava/io/PrintStream;
       8: ldc           #4                  // String Synchronize
      10: invokevirtual #5                  // Method java/io/PrintStream.println:(Ljava/lang/String;)V
      13: aload_1
      **14: monitorexit**
      15: goto          23
      18: astore_2
      19: aload_1
      20: monitorexit
      21: aload_2
      22: athrow
      23: return
    Exception table:
       from    to  target type
           5    15    18   any
          18    21    18   any
}
```

可以看到在同步块的入口和出口分别有 `monitorenter,monitorexit` 指令。

## 锁优化

`synchronized` 很多都称之为重量锁，`JDK1.6` 中对 `synchronized` 进行了各种优化，为了能减少获取和释放锁带来的消耗引入了`偏向锁`和`轻量锁`。

### 轻量锁

当代码进入同步块时，如果同步对象为无锁状态时，当前线程会在栈帧中创建一个锁记录(`Lock Record`)区域，同时将锁对象的对象头中 `Mark Word` 拷贝到锁记录中，再尝试使用 `CAS` 将 `Mark Word` 更新为指向锁记录的指针。

如果更新**成功**，当前线程就获得了锁。

如果更新**失败** `JVM` 会先检查锁对象的 `Mark Word` 是否指向当前线程的锁记录。

如果是则说明当前线程拥有锁对象的锁，可以直接进入同步块。

不是则说明有其他线程抢占了锁，如果存在多个线程同时竞争一把锁，**轻量锁就会膨胀为重量锁**。

#### 解锁

轻量锁的解锁过程也是利用 `CAS` 来实现的，会尝试锁记录替换回锁对象的 `Mark Word` 。如果替换成功则说明整个同步操作完成，失败则说明有其他线程尝试获取锁，这时就会唤醒被挂起的线程(此时已经膨胀为`重量锁`)

轻量锁能提升性能的原因是：

认为大多数锁在整个同步周期都不存在竞争，所以使用 `CAS` 比使用互斥开销更少。但如果锁竞争激烈，轻量锁就不但有互斥的开销，还有 `CAS` 的开销，甚至比重量锁更慢。

### 偏向锁

为了进一步的降低获取锁的代价，`JDK1.6` 之后还引入了偏向锁。

偏向锁的特征是:锁不存在多线程竞争，并且应由一个线程多次获得锁。

当线程访问同步块时，会使用 `CAS` 将线程 ID 更新到锁对象的 `Mark Word` 中，如果更新成功则获得偏向锁，并且之后每次进入这个对象锁相关的同步块时都不需要再次获取锁了。

#### 释放锁

当有另外一个线程获取这个锁时，持有偏向锁的线程就会释放锁，释放时会等待全局安全点(这一时刻没有字节码运行)，接着会暂停拥有偏向锁的线程，根据锁对象目前是否被锁来判定将对象头中的 `Mark Word` 设置为无锁或者是轻量锁状态。

偏向锁可以提高带有同步却没有竞争的程序性能，但如果程序中大多数锁都存在竞争时，那偏向锁就起不到太大作用。可以使用 `-XX:-UseBiasedLocking` 来关闭偏向锁，并默认进入轻量锁。

### 其他优化

#### 适应性自旋

在使用 `CAS` 时，如果操作失败，`CAS` 会自旋再次尝试。由于自旋是需要消耗 `CPU` 资源的，所以如果长期自旋就白白浪费了 `CPU`。`JDK1.6`加入了适应性自旋:

> 如果某个锁自旋很少成功获得，那么下一次就会减少自旋。



# 对锁的一些认知 有哪些锁

## 同一进程

### 重入锁

使用 `ReentrantLock` 获取锁的时候会判断当前线程是否为获取锁的线程，如果是则将同步的状态 +1 ,释放锁的时候则将状态 -1。只有将同步状态的次数置为 0 的时候才会最终释放锁。

### 读写锁

使用 `ReentrantReadWriteLock` ,同时维护一对锁：读锁和写锁。当写线程访问时则其他所有锁都将阻塞，读线程访问时则不会。通过读写锁的分离可以很大程度的提高并发量和吞吐量。

## 不同进程

分布式锁：

### 基于数据库

可以创建一张表，将其中的某个字段设置为`唯一索引`，当多个请求过来的时候只有新建记录成功的请求才算获取到锁，当使用完毕删除这条记录的时候即释放锁。

存在的问题:

- 数据库单点问题，挂了怎么办？
- 不是重入锁，同一进程无法在释放锁之前再次获得锁，因为数据库中已经存在了一条记录了。
- 锁是非阻塞的，一旦 `insert` 失败则会立即返回，并不会进入阻塞队列只能下一次再次获取。
- 锁没有失效时间，如果那个进程解锁失败那就没有请求可以再次获取锁了。

解决方案:

- 数据库切换为主从，不存在单点。
- 在表中加入一个同步状态字段，每次获取锁的是加 1 ，释放锁的时候`-1`，当状态为 0 的时候就删除这条记录，即释放锁。
- 非阻塞的情况可以用 `while` 循环来实现，循环的时候记录时间，达到 X 秒记为超时，`break`。
- 可以开启一个定时任务每隔一段时间扫描找出多少 X 秒都没有被删除的记录，主动删除这条记录。

### 基于 Redis

使用 `setNX(key) setEX(timeout)` 命令，只有在该 `key` 不存在的时候创建这个 `key`，就相当于获取了锁。由于有超时时间，所以过了规定时间会自动删除，这样也可以避免死锁。

可以参考：

[基于 Redis 的分布式锁](http://crossoverjie.top/2018/03/29/distributed-lock/distributed-lock-redis/)

### 基于 ZK







# ReentrantLock 实现原理

使用 `synchronized` 来做同步处理时，锁的获取和释放都是隐式的，实现的原理是通过编译后加上不同的机器指令来实现。

而 `ReentrantLock` 就是一个普通的类，它是基于 `AQS(AbstractQueuedSynchronizer)`来实现的。

是一个**重入锁**：一个线程获得了锁之后仍然可以**反复**的加锁，不会出现自己阻塞自己的情况。

> `AQS` 是 `Java` 并发包里实现锁、同步的一个重要的基础框架。

## 锁类型

ReentrantLock 分为**公平锁**和**非公平锁**，可以通过构造方法来指定具体类型：

```
    //默认非公平锁
    public ReentrantLock() {
        sync = new NonfairSync();
    }
    
    //公平锁
    public ReentrantLock(boolean fair) {
        sync = fair ? new FairSync() : new NonfairSync();
    }
```

默认一般使用**非公平锁**，它的效率和吞吐量都比公平锁高的多(后面会分析具体原因)。

## 获取锁

通常的使用方式如下:

```
    private ReentrantLock lock = new ReentrantLock();
    public void run() {
        lock.lock();
        try {
            //do bussiness
        } catch (InterruptedException e) {
            e.printStackTrace();
        } finally {
            lock.unlock();
        }
    }
```

### 公平锁获取锁

首先看下获取锁的过程：

```
    public void lock() {
        sync.lock();
    }
```

可以看到是使用 `sync`的方法，而这个方法是一个抽象方法，具体是由其子类(`FairSync`)来实现的，以下是公平锁的实现:

```java
        final void lock() {
            acquire(1);
        }
        
        //AbstractQueuedSynchronizer 中的 acquire()
        public final void acquire(int arg) {
        if (!tryAcquire(arg) &&
            acquireQueued(addWaiter(Node.EXCLUSIVE), arg))
            selfInterrupt();
    	}
```

第一步是尝试获取锁(`tryAcquire(arg)`),这个也是由其子类实现：

```java
        protected final boolean tryAcquire(int acquires) {
            final Thread current = Thread.currentThread();
            int c = getState();
            if (c == 0) {
                if (!hasQueuedPredecessors() &&
                    compareAndSetState(0, acquires)) {
                    setExclusiveOwnerThread(current);
                    return true;
                }
            }
            else if (current == getExclusiveOwnerThread()) {
                int nextc = c + acquires;
                if (nextc < 0)
                    throw new Error("Maximum lock count exceeded");
                setState(nextc);
                return true;
            }
            return false;
        }
    }
```

首先会判断 `AQS` 中的 `state` 是否等于 0，0 表示目前没有其他线程获得锁，当前线程就可以尝试获取锁。

**注意**:尝试之前会利用 `hasQueuedPredecessors()` 方法来判断 AQS 的队列中中是否有其他线程，如果有则不会尝试获取锁(**这是公平锁特有的情况**)。

如果队列中没有线程就利用 CAS 来将 AQS 中的 state 修改为1，也就是获取锁，获取成功则将当前线程置为获得锁的独占线程(`setExclusiveOwnerThread(current)`)。

如果 `state` 大于 0 时，说明锁已经被获取了，则需要判断获取锁的线程是否为当前线程(`ReentrantLock` 支持重入)，是则需要将 `state + 1`，并将值更新。

#### 写入队列

如果 `tryAcquire(arg)` 获取锁失败，则需要用 `addWaiter(Node.EXCLUSIVE)` 将当前线程写入队列中。

写入之前需要将当前线程包装为一个 `Node` 对象(`addWaiter(Node.EXCLUSIVE)`)。

> AQS 中的队列是由 Node 节点组成的双向链表实现的。

包装代码:

```java
    private Node addWaiter(Node mode) {
        Node node = new Node(Thread.currentThread(), mode);
        // Try the fast path of enq; backup to full enq on failure
        Node pred = tail;
        if (pred != null) {
            node.prev = pred;
            if (compareAndSetTail(pred, node)) {
                pred.next = node;
                return node;
            }
        }
        enq(node);
        return node;
    }
```

首先判断队列是否为空，不为空时则将封装好的 `Node` 利用 `CAS` 写入队尾，如果出现并发写入失败就需要调用 `enq(node);` 来写入了。

```java
    private Node enq(final Node node) {
        for (;;) {
            Node t = tail;
            if (t == null) { // Must initialize
                if (compareAndSetHead(new Node()))
                    tail = head;
            } else {
                node.prev = t;
                if (compareAndSetTail(t, node)) {
                    t.next = node;
                    return t;
                }
            }
        }
    }
```

这个处理逻辑就相当于`自旋`加上 `CAS` 保证一定能写入队列。

#### 挂起等待线程

写入队列之后需要将当前线程挂起(利用`acquireQueued(addWaiter(Node.EXCLUSIVE), arg)`)：

```java
    final boolean acquireQueued(final Node node, int arg) {
        boolean failed = true;
        try {
            boolean interrupted = false;
            for (;;) {
                final Node p = node.predecessor();
                if (p == head && tryAcquire(arg)) {
                    setHead(node);
                    p.next = null; // help GC
                    failed = false;
                    return interrupted;
                }
                if (shouldParkAfterFailedAcquire(p, node) &&
                    parkAndCheckInterrupt())
                    interrupted = true;
            }
        } finally {
            if (failed)
                cancelAcquire(node);
        }
    }
```

首先会根据 `node.predecessor()` 获取到上一个节点是否为头节点，如果是则尝试获取一次锁，获取成功就万事大吉了。

如果不是头节点，或者获取锁失败，则会根据上一个节点的 `waitStatus` 状态来处理(`shouldParkAfterFailedAcquire(p, node)`)。

`waitStatus` 用于记录当前节点的状态，如节点取消、节点等待等。

`shouldParkAfterFailedAcquire(p, node)` 返回当前线程是否需要挂起，如果需要则调用 `parkAndCheckInterrupt()`：

```java
    private final boolean parkAndCheckInterrupt() {
        LockSupport.park(this);
        return Thread.interrupted();
    }
```

他是利用 `LockSupport` 的 `part` 方法来挂起当前线程的，直到被唤醒。

### 非公平锁获取锁

公平锁与非公平锁的差异主要在获取锁：

公平锁就相当于买票，后来的人需要排到队尾依次买票，**不能插队**。

而非公平锁则没有这些规则，是**抢占模式**，每来一个人不会去管队列如何，直接尝试获取锁。

非公平锁:

```java
        final void lock() {
            //直接尝试获取锁
            if (compareAndSetState(0, 1))
                setExclusiveOwnerThread(Thread.currentThread());
            else
                acquire(1);
        }
```

公平锁:

```java
        final void lock() {
            acquire(1);
        }
```

还要一个重要的区别是在尝试获取锁时`tryAcquire(arg)`，非公平锁是不需要判断队列中是否还有其他线程，也是直接尝试获取锁：

```java
        final boolean nonfairTryAcquire(int acquires) {
            final Thread current = Thread.currentThread();
            int c = getState();
            if (c == 0) {
                //没有 !hasQueuedPredecessors() 判断
                if (compareAndSetState(0, acquires)) {
                    setExclusiveOwnerThread(current);
                    return true;
                }
            }
            else if (current == getExclusiveOwnerThread()) {
                int nextc = c + acquires;
                if (nextc < 0) // overflow
                    throw new Error("Maximum lock count exceeded");
                setState(nextc);
                return true;
            }
            return false;
        }
```

## 释放锁

公平锁和非公平锁的释放流程都是一样的：

```java
    public void unlock() {
        sync.release(1);
    }
    
    public final boolean release(int arg) {
        if (tryRelease(arg)) {
            Node h = head;
            if (h != null && h.waitStatus != 0)
            	   //唤醒被挂起的线程
                unparkSuccessor(h);
            return true;
        }
        return false;
    }
    
    //尝试释放锁
    protected final boolean tryRelease(int releases) {
        int c = getState() - releases;
        if (Thread.currentThread() != getExclusiveOwnerThread())
            throw new IllegalMonitorStateException();
        boolean free = false;
        if (c == 0) {
            free = true;
            setExclusiveOwnerThread(null);
        }
        setState(c);
        return free;
    }        
```

首先会判断当前线程是否为获得锁的线程，由于是重入锁所以需要将 `state` 减到 0 才认为完全释放锁。

释放之后需要调用 `unparkSuccessor(h)` 来唤醒被挂起的线程。

## 总结

由于公平锁需要关心队列的情况，得按照队列里的先后顺序来获取锁(会造成大量的线程上下文切换)，而非公平锁则没有这个限制。

所以也就能解释非公平锁的效率会被公平锁更高。